hermes_ai/__init__.py
hermes_ai/main.py
hermes_ai/data/__init__.py
hermes_ai/data/messages_actions.csv
hermes_ai/data/synthetic_messages.csv
hermes_ai/models/__init__.py
hermes_ai/models/classifier.py
hermes_ai/models/classifier_model
hermes_ai/models/data_processor.py
hermes_ai/models/vectorizer
hermes_ai/models/__pycache__/__init__.cpython-38.pyc
hermes_ai/models/__pycache__/classifier.cpython-38.pyc
hermes_ai/models/__pycache__/data_processor.cpython-38.pyc
hermes_ai-0.1.9.dist-info/METADATA
hermes_ai-0.1.9.dist-info/WHEEL
hermes_ai-0.1.9.dist-info/top_level.txt
hermes_ai-0.1.9.dist-info/RECORD
