Metadata-Version: 2.1
Name: hermes-ai
Version: 0.1.9
Summary: A ML model to classify messages, reply and summarize conversations
Home-page: https://github.com/Talos-IA-Lab/hermes
Author: Jose Ruben Maldonado Herrera
Author-email: rub.maler.22@gmail.com
Classifier: Programming Language :: Python :: 3
Classifier: License :: OSI Approved :: MIT License
Classifier: Operating System :: OS Independent
Requires-Python: >=3.6
Requires-Dist: joblib
Requires-Dist: nltk
Requires-Dist: numpy
Requires-Dist: pandas
Requires-Dist: scikit-learn
